veracode_api_py/__init__.py
veracode_api_py/analytics.py
veracode_api_py/api.py
veracode_api_py/apihelper.py
veracode_api_py/applications.py
veracode_api_py/collections.py
veracode_api_py/constants.py
veracode_api_py/dast.py
veracode_api_py/dynamic.py
veracode_api_py/exceptions.py
veracode_api_py/findings.py
veracode_api_py/healthcheck.py
veracode_api_py/identity.py
veracode_api_py/log.py
veracode_api_py/policy.py
veracode_api_py/sca.py
veracode_api_py/static.py
veracode_api_py/xmlapi.py
veracode_api_py-0.9.64.dist-info/licenses/LICENSE.txt
veracode_api_py-0.9.64.dist-info/METADATA
veracode_api_py-0.9.64.dist-info/WHEEL
veracode_api_py-0.9.64.dist-info/top_level.txt
veracode_api_py-0.9.64.dist-info/RECORD
